zyjxcswe/__init__.py
zyjxcswe/son.py
zyjxcswe-0.0.2.dist-info/METADATA
zyjxcswe-0.0.2.dist-info/WHEEL
zyjxcswe-0.0.2.dist-info/top_level.txt
zyjxcswe-0.0.2.dist-info/RECORD
