Metadata-Version: 2.1
Name: zyjxcswe
Version: 0.0.2
Summary: gk first demo
Home-page: UNKNOWN
Author: laomaoQAQ
Author-email: 17863923011@163.com
License: apache 3.0
Platform: UNKNOWN
